zimscraperlib/__about__.py
zimscraperlib/__init__.py
zimscraperlib/constants.py
zimscraperlib/download.py
zimscraperlib/filesystem.py
zimscraperlib/fix_ogvjs_dist.py
zimscraperlib/html.py
zimscraperlib/i18n.py
zimscraperlib/inputs.py
zimscraperlib/logging.py
zimscraperlib/misc.py
zimscraperlib/py.typed
zimscraperlib/types.py
zimscraperlib/typing.py
zimscraperlib/uri.py
zimscraperlib/image/__init__.py
zimscraperlib/image/conversion.py
zimscraperlib/image/illustration.py
zimscraperlib/image/optimization.py
zimscraperlib/image/presets.py
zimscraperlib/image/probing.py
zimscraperlib/image/transformation.py
zimscraperlib/image/utils.py
zimscraperlib/rewriting/__init__.py
zimscraperlib/rewriting/css.py
zimscraperlib/rewriting/html.py
zimscraperlib/rewriting/js.py
zimscraperlib/rewriting/rules.py
zimscraperlib/rewriting/rx_replacer.py
zimscraperlib/rewriting/url_rewriting.py
zimscraperlib/rewriting/statics/README.md
zimscraperlib/rewriting/statics/__wb_module_decl.js
zimscraperlib/rewriting/statics/wombat.js
zimscraperlib/rewriting/statics/wombatSetup.js
zimscraperlib/rewriting/templates/head_insert.html
zimscraperlib/video/__init__.py
zimscraperlib/video/config.py
zimscraperlib/video/encoding.py
zimscraperlib/video/presets.py
zimscraperlib/video/probing.py
zimscraperlib/zim/__init__.py
zimscraperlib/zim/_libkiwix.py
zimscraperlib/zim/archive.py
zimscraperlib/zim/creator.py
zimscraperlib/zim/dedup.py
zimscraperlib/zim/filesystem.py
zimscraperlib/zim/indexing.py
zimscraperlib/zim/items.py
zimscraperlib/zim/metadata.py
zimscraperlib/zim/providers.py
zimscraperlib-5.3.0.dist-info/METADATA
zimscraperlib-5.3.0.dist-info/WHEEL
zimscraperlib-5.3.0.dist-info/entry_points.txt
zimscraperlib-5.3.0.dist-info/licenses/LICENSE
zimscraperlib-5.3.0.dist-info/RECORD
