Metadata-Version: 2.4
Name: zimscraperlib
Version: 5.3.0
Summary: Collection of python tools to re-use common code across scrapers
Project-URL: Donate, https://www.kiwix.org/en/support-us/
Project-URL: Homepage, https://github.com/openzim/python-scraperlib
Author-email: openZIM <dev@openzim.org>
License: GPL-3.0-or-later
License-File: LICENSE
Keywords: offline,openzim,zim
Classifier: Development Status :: 5 - Production/Stable
Classifier: Intended Audience :: Developers
Classifier: License :: OSI Approved :: GNU General Public License v3 or later (GPLv3+)
Classifier: Programming Language :: Python :: 3
Classifier: Programming Language :: Python :: 3.14
Requires-Python: <3.15,>=3.14
Requires-Dist: babel<3.0,>=2.9
Requires-Dist: beartype<0.23,>=0.19
Requires-Dist: beautifulsoup4<5.0,>=4.9.3
Requires-Dist: cairosvg<3.0,>=2.2.0
Requires-Dist: colorthief==0.2.1
Requires-Dist: idna<4.0,>=2.5
Requires-Dist: iso639-lang<3.0,>=2.4.0
Requires-Dist: libzim<4.0,>=3.8.0
Requires-Dist: lxml<7.0,>=4.6.3
Requires-Dist: optimize-images<2.0,>=1.3.6
Requires-Dist: piexif==1.1.3
Requires-Dist: pillow<13.0,>=7.0.0
Requires-Dist: pymupdf<2.0,>=1.24.0
Requires-Dist: python-magic<0.5,>=0.4.3
Requires-Dist: python-resize-image<1.2,>=1.1.19
Requires-Dist: regex>=2020.7.14
Requires-Dist: requests<3.0,>=2.25.1
Requires-Dist: types-xxhash<4.0,>=2.0
Requires-Dist: urllib3<2.6.0,>=1.26.5
Requires-Dist: xxhash<4.0,>=2.0
Requires-Dist: yt-dlp
Provides-Extra: check
Requires-Dist: pyright==1.1.407; extra == 'check'
Requires-Dist: pytest==9.0.1; extra == 'check'
Provides-Extra: dev
Requires-Dist: black==25.11.0; extra == 'dev'
Requires-Dist: coverage==7.11.3; extra == 'dev'
Requires-Dist: invoke==2.2.1; extra == 'dev'
Requires-Dist: ipython==9.7.0; extra == 'dev'
Requires-Dist: jinja2==3.1.6; extra == 'dev'
Requires-Dist: mkdocs-gen-files==0.5.0; extra == 'dev'
Requires-Dist: mkdocs-include-markdown-plugin==7.2.0; extra == 'dev'
Requires-Dist: mkdocs-literate-nav==0.6.2; extra == 'dev'
Requires-Dist: mkdocs-material==9.7.0; extra == 'dev'
Requires-Dist: mkdocs==1.6.1; extra == 'dev'
Requires-Dist: mkdocstrings[python]==0.30.1; extra == 'dev'
Requires-Dist: pre-commit==4.4.0; extra == 'dev'
Requires-Dist: pymdown-extensions==10.17.1; extra == 'dev'
Requires-Dist: pyright==1.1.407; extra == 'dev'
Requires-Dist: pytest-mock==3.15.1; extra == 'dev'
Requires-Dist: pytest==9.0.1; extra == 'dev'
Requires-Dist: pyyaml==6.0.3; extra == 'dev'
Requires-Dist: ruff==0.14.5; extra == 'dev'
Provides-Extra: docs
Requires-Dist: mkdocs-gen-files==0.5.0; extra == 'docs'
Requires-Dist: mkdocs-include-markdown-plugin==7.2.0; extra == 'docs'
Requires-Dist: mkdocs-literate-nav==0.6.2; extra == 'docs'
Requires-Dist: mkdocs-material==9.7.0; extra == 'docs'
Requires-Dist: mkdocs==1.6.1; extra == 'docs'
Requires-Dist: mkdocstrings[python]==0.30.1; extra == 'docs'
Requires-Dist: pymdown-extensions==10.17.1; extra == 'docs'
Provides-Extra: lint
Requires-Dist: black==25.11.0; extra == 'lint'
Requires-Dist: ruff==0.14.5; extra == 'lint'
Provides-Extra: scripts
Requires-Dist: invoke==2.2.1; extra == 'scripts'
Requires-Dist: jinja2==3.1.6; extra == 'scripts'
Requires-Dist: pyyaml==6.0.3; extra == 'scripts'
Provides-Extra: test
Requires-Dist: coverage==7.11.3; extra == 'test'
Requires-Dist: pytest-mock==3.15.1; extra == 'test'
Requires-Dist: pytest==9.0.1; extra == 'test'
